setuptools_pep660/__init__.py
setuptools_pep660/editable_wheel.py
setuptools_pep660-0.1.4.dist-info/METADATA
setuptools_pep660-0.1.4.dist-info/WHEEL
setuptools_pep660-0.1.4.dist-info/entry_points.txt
setuptools_pep660-0.1.4.dist-info/top_level.txt
setuptools_pep660-0.1.4.dist-info/RECORD
